[{"name":"king arthur","password":"password1","profession":"king","id":1},{"name":"rob kendal","password":"password3","profession":"code fiddler","id":2},{"name":"teresa may","password":"password2","profession":"brexit destroyer","id":6},{"name":"Chance favors only those who know how to court her.","password":"Charles Nicolle","profession":10,"id":4},{"name":"Chance favors only those who know how to court her.","password":"Charles Nicolle","profession":10,"id":5},{"name":"Chance favors only those who know how to court her.","password":"Charles Nicolle","profession":10,"id":6},{"name":"Chance favors only those who know how to court her.","password":"Charles Nicolle","profession":10,"id":7},{"name":"Chance favors only those who know how to court her.","password":"Charles Nicolle","profession":10,"id":8},{"name":"Chance favors only those who know how to court her.","password":"Charles Nicolle","profession":10,"id":9},{"name":"Chance favors only those who know how to court her.","password":"Charles Nicolle","profession":10,"id":10},{"name":"Chance favors only those who know how to court her.","password":"Charles Nicolle","profession":10,"id":11},{"name":"Chance favors only those who know how to court her.","password":"Charles Nicolle","profession":10,"id":12},{"name":"Chance favors only those who know how to court her.","password":"Charles Nicolle","profession":10,"id":13},{"name":"Chance favors only those who know how to court her.","password":"Charles Nicolle","profession":10,"id":14},{"name":"Chance favors only those who know how to court her.","password":"Charles Nicolle","profession":10,"id":15},{"name":"Chance favors only those who know how to court her.","password":"Charles Nicolle","profession":10,"id":16},{"name":"Chance favors only those who know how to court her.","password":"Charles Nicolle","profession":10,"id":17},{"name":"Chance favors only those who know how to court her.","password":"Charles Nicolle","profession":10,"id":18},{"name":"Chance favors only those who know how to court her.","password":"Charles Nicolle","profession":"10","id":19},{"name":"Chance favors only those who know how to court her.","password":"Charles Nicolle","profession":"10","id":20},{"name":"Chance favors only those who know how to court her.","password":"Charles Nicolle","profession":"10","id":21},{"name":"Chance favors only those who know how to court her.","password":"Charles Nicolle","profession":"10","id":22},{"name":"Chance favors only those who know how to court her.","password":"Charles Nicolle","profession":"10","id":23},{"name":"Chance favors only those who know how to court her.","password":"Charles Nicolle","profession":"10","id":24},{"name":"Chance favors only those who know how to court her.","password":"Charles Nicolle","profession":"10","id":25},{"name":"Chance favors only those who know how to court her.","password":"Charles Nicolle","profession":"10","id":26},{"name":"Chance favors only those who know how to court her.","password":"Charles Nicolle","profession":"10","id":27},{"name":"Chance favors only those who know how to court her.","password":"Charles Nicolle","profession":"10","id":28},{"name":"Chance favors only those who know how to court her.","password":"Charles Nicolle","profession":"10","id":29},{"name":"Chance favors only those who know how to court her.","password":"Charles Nicolle","profession":"10","id":30},{"name":"Chance favors only those who know how to court her.","password":"Charles Nicolle","profession":"10","id":31},{"name":"Chance favors only those who know how to court her.","password":"Charles Nicolle","profession":"10","id":32},{"name":"Chance favors only those who know how to court her.","password":"Charles Nicolle","profession":"10","id":33},{"name":"Chance favors only those who know how to court her.","password":"Charles Nicolle","profession":"10","id":34},{"name":"Chance favors only those who know how to court her.","password":"Charles Nicolle","profession":"10","id":35},{"name":"Chance favors only those who know how to court her.","password":"Charles Nicolle","profession":"10","id":36},{"name":"Chance favors only those who know how to court her.","password":"Charles Nicolle","profession":"10","id":37},{"name":"Chance favors only those who know how to court her.","password":"Charles Nicolle","profession":"10","id":38},{"name":"Chance favors only those who know how to court her.","password":"Charles Nicolle","profession":"10","id":39},{"name":"Chance favors only those who know how to court her.","password":"Charles Nicolle","profession":"10","id":40},{"name":"Chance favors only those who know how to court her.","password":"Charles Nicolle","profession":"10","id":41},{"name":"Chance favors only those who know how to court her.","password":"Charles Nicolle","profession":"10","id":42},{"name":"Chance favors only those who know how to court her.","password":"Charles Nicolle","profession":"10","id":43},{"name":"Chance favors only those who know how to court her.","password":"Charles Nicolle","profession":"10","id":44},{"name":"Chance favors only those who know how to court her.","password":"Charles Nicolle","profession":"10","id":45},{"email":"john.louis@gmail.com","password":"p4ssw0rd","profileId":"1","id":46},{"email":"john.louis@gmail.com","password":"p4ssw0rd","profileId":"1","id":47},{"email":"john.louis@gmail.com","password":"p4ssw0rd","profileId":"1","id":48},{"email":"john.louis@gmail.com","password":"p4ssw0rd","profileId":"1","id":49},{"email":"john.louis@gmail.com","password":"p4ssw0rd","profileId":"1","id":50},{"email":"john.louis@gmail.com","password":"p4ssw0rd","profileId":"1","id":51},{"email":"john.louis@gmail.com","password":"p4ssw0rd","profileId":"1","id":52},{"email":"john.louis@gmail.com","password":"p4ssw0rd","profileId":"1","id":53},{"email":"john.louis@gmail.com","password":"p4ssw0rd","profileId":"1","id":54},{"email":"john.louis@gmail.com","password":"p4ssw0rd","profileId":"1","id":55},{"email":"john.louis@gmail.com","password":"p4ssw0rd","profileId":"1","id":56},{"email":"john.louis@gmail.com","password":"p4ssw0rd","profileId":"1","id":57},{"email":"john.louis@gmail.com","password":"p4ssw0rd","profileId":"1","id":58},{"email":"john.louis@gmail.com","password":"p4ssw0rd","profileId":"1","id":59},{"email":"john.louis@gmail.com","password":"p4ssw0rd","profileId":"1","id":60},{"email":"john.louis@gmail.com","password":"p4ssw0rd","profileId":"1","id":61},{"email":"john.louis@gmail.com","password":"p4ssw0rd","profileId":"1","id":62},{"email":"john.louis@gmail.com","password":"p4ssw0rd","profileId":"1","id":63},{"email":"john.louis@gmail.com","password":"p4ssw0rd","profileId":"1","id":64},{"email":"john.louis@gmail.com","password":"p4ssw0rd","profileId":"1","id":65},{"email":"john.louis@gmail.com","password":"p4ssw0rd","profileId":"1","id":66},{"email":"john.louis@gmail.com","password":"p4ssw0rd","profileId":"1","id":67},{"email":"john.louis@gmail.com","password":"p4ssw0rd","profileId":"1","id":68},{"email":"john.louis@gmail.com","password":"p4ssw0rd","profileId":"1","id":69},{"email":"john.louis@gmail.com","password":"p4ssw0rd","profileId":"1","id":70},{"email":"john.louis@gmail.com","password":"p4ssw0rd","profileId":"1","id":71},{"email":"john.louis@gmail.com","password":"p4ssw0rd","profileId":"1","id":72},{"email":"john.louis@gmail.com","password":"p4ssw0rd","profileId":"1","id":73},{"email":"john.louis@gmail.com","password":"p4ssw0rd","profileId":"1","id":74},{"email":"john.louis@gmail.com","password":"p4ssw0rd","profileId":"1","id":75},{"email":"john.louis@gmail.com","password":"p4ssw0rd","profileId":"1","id":76},{"email":"john.louis@gmail.com","password":"p4ssw0rd","profileId":"1","id":77},{"email":"john.louis@gmail.com","password":"p4ssw0rd","profileId":"1","id":78},{"email":"john.louis@gmail.com","password":"p4ssw0rd","profileId":"1","id":79},{"email":"john.louis@gmail.com","password":"p4ssw0rd","profileId":"1","id":80},{"email":"john.louis@gmail.com","password":"p4ssw0rd","profileId":"1","id":81},{"email":"john.louis@gmail.com","password":"p4ssw0rd","profileId":"1","id":82},{"email":"john.louis@gmail.com","password":"p4ssw0rd","profileId":"1","id":83},{"email":"john.louis@gmail.com","password":"p4ssw0rd","profileId":"1","id":84},{"email":"john.louis@gmail.com","password":"p4ssw0rd","profileId":"1","id":85},{"email":"john.louis@gmail.com","password":"p4ssw0rd","profileId":"1","id":86},{"email":"john.louis@gmail.com","password":"p4ssw0rd","profileId":"1","id":87},{"email":"john.louis@gmail.com","password":"p4ssw0rd","profileId":"1","id":88},{"email":"john.louis@gmail.com","password":"p4ssw0rd","profileId":"1","id":89},{"email":"john.louis@gmail.com","password":"p4ssw0rd","profileId":"1","id":90},{"email":"john.louis@gmail.com","password":"p4ssw0rd","profileId":"1","id":91},{"email":"john.louis@gmail.com","password":"p4ssw0rd","profileId":"1","id":92},{"email":"john.louis@gmail.com","password":"p4ssw0rd","profileId":"1","id":93},{"email":"john.louis@gmail.com","password":"p4ssw0rd","profileId":"1","id":94},{"email":"john.louis@gmail.com","password":"p4ssw0rd","profileId":"1","id":95},{"email":"john.louis@gmail.com","password":"p4ssw0rd","profileId":"1","id":96},{"email":"john.louis@gmail.com","password":"p4ssw0rd","profileId":"1","id":97},{"email":"john.louis@gmail.com","password":"p4ssw0rd","profileId":"1","id":98},{"email":"john.louis@gmail.com","password":"p4ssw0rd","profileId":"1","id":99},{"email":"john.louis@gmail.com","password":"p4ssw0rd","profileId":"1","id":100},{"email":"john.louis@gmail.com","password":"p4ssw0rd","profileId":"1","id":101}]